pptestkrzysiekmarut/__init__.py
pptestkrzysiekmarut/m_mod_pptest.py
pptestkrzysiekmarut-0.0.1.dist-info/LICENCE.txt
pptestkrzysiekmarut-0.0.1.dist-info/METADATA
pptestkrzysiekmarut-0.0.1.dist-info/WHEEL
pptestkrzysiekmarut-0.0.1.dist-info/top_level.txt
pptestkrzysiekmarut-0.0.1.dist-info/RECORD
