Metadata-Version: 2.1
Name: pptestkrzysiekmarut
Version: 0.0.1
Summary: My test package
Author-email: KM <marut.krzysztof6@gmail.com>
License: MIT License
Keywords: pptestkrzysiekmarut,myfirstfunctions,name,surname,personal data
Classifier: Framework :: IDLE
Classifier: License :: Free For Educational Use
Requires-Python: >=3.0
License-File: LICENCE.txt
Requires-Dist: numpy ; python_version >= "3.0"
